efficientCV/__init__.py
efficientCV/layers/__init__.py
efficientCV/layers/convolutions.py
efficientCV/models/__init__.py
efficientCV/models/efficientnet_v1.py
efficientCV/models/efficientnet_v2.py
efficientCV/models/mobilenet_v1.py
efficientCV/models/mobilenet_v2.py
efficientCV/utils/__init__.py
efficientCV/utils/ops.py
efficientCV/utils/utils.py
efficientCV-0.0.3.dist-info/METADATA
efficientCV-0.0.3.dist-info/WHEEL
efficientCV-0.0.3.dist-info/top_level.txt
efficientCV-0.0.3.dist-info/RECORD
