Metadata-Version: 2.1
Name: efficientCV
Version: 0.0.3
Summary: Computational efficient models for computer vision
Home-page: https://github.com/minkhent/efficientnets
Author: Min Khent
Author-email: minkhent.dev@gmail.com
Classifier: Programming Language :: Python :: 3
Classifier: License :: OSI Approved :: MIT License
Classifier: Operating System :: OS Independent
Requires-Python: >=3.10
Requires-Dist: torch
Requires-Dist: numpy
